funcparserlib/__init__.py
funcparserlib/lexer.py
funcparserlib/lexer.pyi
funcparserlib/parser.py
funcparserlib/parser.pyi
funcparserlib/py.typed
funcparserlib/util.py
funcparserlib/util.pyi
funcparserlib-1.0.0a2.dist-info/LICENSE
funcparserlib-1.0.0a2.dist-info/WHEEL
funcparserlib-1.0.0a2.dist-info/METADATA
funcparserlib-1.0.0a2.dist-info/RECORD
